restgfdl/GetExchangeMessages.py
restgfdl/GetExchangeSnapshot.py
restgfdl/GetExchanges.py
restgfdl/GetExpiryDates.py
restgfdl/GetHistory.py
restgfdl/GetInstrumentTypes.py
restgfdl/GetInstruments.py
restgfdl/GetInstrumentsOnSearch.py
restgfdl/GetLastQuote.py
restgfdl/GetLastQuoteArray.py
restgfdl/GetLastQuoteArrayOptionGreeks.py
restgfdl/GetLastQuoteArrayShort.py
restgfdl/GetLastQuoteArrayShortWithClose.py
restgfdl/GetLastQuoteOptionChain.py
restgfdl/GetLastQuoteOptionGreeks.py
restgfdl/GetLastQuoteOptionGreeksChain.py
restgfdl/GetLastQuoteShort.py
restgfdl/GetLastQuoteShortWithClose.py
restgfdl/GetLimitation.py
restgfdl/GetMarketMessages.py
restgfdl/GetOptionTypes.py
restgfdl/GetProducts.py
restgfdl/GetServerInfo.py
restgfdl/GetSnapshot.py
restgfdl/GetStrikePrices.py
restgfdl/__init__.py
restgfdl/base_api.py
restgfdl-1.1.5.dist-info/METADATA
restgfdl-1.1.5.dist-info/WHEEL
restgfdl-1.1.5.dist-info/top_level.txt
restgfdl-1.1.5.dist-info/RECORD
